argconfig.py
argconfig/argconfig.py
argconfig-0.0.1.dist-info/LICENSE
argconfig-0.0.1.dist-info/METADATA
argconfig-0.0.1.dist-info/WHEEL
argconfig-0.0.1.dist-info/top_level.txt
argconfig-0.0.1.dist-info/RECORD
