Metadata-Version: 2.1
Name: argconfig
Version: 0.0.1
Summary: Argparse enhanced with a config file to overwrite code-based defaults
Home-page: https://github.com/patrick-c-odriscoll/argconfig
Author: Patrick C O'Driscoll
Author-email: patrick.c.odriscoll@gmail.com
License: MIT
Keywords: CLI configuration arguments parsing
Platform: UNKNOWN
Classifier: Development Status :: 4 - Beta
Classifier: Intended Audience :: Developers
Classifier: License :: OSI Approved :: MIT License
Classifier: Programming Language :: Python
Requires-Dist: pyyaml
Requires-Dist: argparse
